constructio-sdk/__init__.py
constructio_sdk/__init__.py
constructio_sdk/compute.py
constructio_sdk/prepare.py
constructio_sdk/simulation.py
tests/__init__.py
tests/test_compute.py
tests/test_prepare.py
constructio_sdk-0.10.0.dist-info/LICENSE
constructio_sdk-0.10.0.dist-info/METADATA
constructio_sdk-0.10.0.dist-info/WHEEL
constructio_sdk-0.10.0.dist-info/top_level.txt
constructio_sdk-0.10.0.dist-info/RECORD
