Metadata-Version: 2.1
Name: constructio-sdk
Version: 0.10.0
Summary: Constructio SDK
Home-page: https://github.com/amocer-idf/constructio-sdk-python
Author: Olivier Hoareau
Author-email: oha+oss@greenberets.io
License: UNKNOWN
Platform: UNKNOWN
Classifier: Programming Language :: Python :: 3
Classifier: License :: OSI Approved :: MIT License
Classifier: Operating System :: OS Independent
Requires-Python: >=3.5
Requires-Dist: requests
